Workbook

Sheet Recommendation
A1: AI Admission Assistant — LLM Path Recommendation
A2: Sarvam (cloud) vs. fully local self-host vs. Bhashini (government) — cost, quality, and what to ship now. Companion to docs/MODELS_AND_DEPLOYMENT.md. Scope: the admission chat/RAG pipeline only — see orderassist-extension-cost-breakdown.xlsx and orderassist-extension-production-cost-estimate.xlsx for the browser extension’s separate cost estimate.
A4: Recommendation
A5: Ship now on Sarvam-primary + local-fallback — the architecture already built in MODELS_AND_DEPLOYMENT.md.
A6: • It is the only path that is both available today and gives the best answer quality — Sarvam-105B is benchmarked as the top open model for Indian-language Q&A (see 'Path Comparison').
A7: • The marginal cost of using Sarvam over a fully-local model is roughly $0.91–$9.10/year across the 1–10 questions/student sensitivity range at 6,000 students, worst-case language mix (see 'Sarvam Cost Projection') — noise next to the $3,026–$4,680/year base hosting cost (Option B–Option A) that is required regardless of which LLM answers the question.
A8: • Raise SARVAM_DAILY_LIMIT (currently 150/day, a POC safety cap) and move to Sarvam's Business rate-limit tier (1,000 req/min) before go-live — the current cap will throttle real traffic on a busy day, not because of cost but because of request-rate ceiling.
A9: • Track Bhashini as a future swap-in, not a blocker. It is government-subsidized and could shrink the Sarvam line further once its enterprise review clears — but its production price is not public yet, and it is a translation/speech layer, not a drop-in replacement for Sarvam's answer-generation model (see 'Path Comparison').
A10: • Upgrade the local fallback model from gemma2:2b to Qwen3-8B at $0 incremental hosting cost (it fits the GPU tier already budgeted) — this is the fix for the failure mode that actually matters: what a student sees when Sarvam is capped or down during a traffic spike.
A12: Key numbers
A13: Metric | B13: Value | C13: Source
A14: Total system cost, first year — Option B (CPU) hosting + Sarvam worst-case API | B14: ='Hosting Options'!J8+'Sarvam Cost Projection'!B31 -> 3034.6634 | C14: Hosting Options + Sarvam Cost Projection
A15: Total system cost, first year — Option A (GPU) hosting + Sarvam worst-case API | B15: ='Hosting Options'!J5+'Sarvam Cost Projection'!B31 -> 4688.8634 | C15: Hosting Options + Sarvam Cost Projection
A16: Sarvam marginal cost/year, worst case (6,000 students, ≤10 Q each, 45% Hindi/Marathi, 0% cache hit) | B16: ='Sarvam Cost Projection'!B31 -> 9.1034483 | C16: Sarvam Cost Projection
A17: Sarvam cost as % of total system cost (GPU option) | B17: ='Sarvam Cost Projection'!B31/B15 -> 0.0019415042 | C17: Calculated
A18: Local-model fallback upgrade (gemma2:2b → Qwen3-8B) incremental hosting cost | B18: ='Local Model Comparison'!G9 -> 0 | C18: Local Model Comparison
A19: Bhashini production price | B19: Not public — blocked in review, contact required | C19: Path Comparison / Assumptions

Sheet Path Comparison
A1: Sarvam vs. Fully Local vs. Bhashini
A2: Side-by-side on what each option actually is, result quality, cost at 6,000-student scale, availability, and risk.
A4: Dimension | B4: Sarvam (cloud primary) | C4: Fully local self-host | D4: Bhashini (government)
A5: What it actually is | B5: Full conversational LLM, purpose-built for Indic Q&A (sarvam-105b) | C5: You run the LLM yourself — e.g. Qwen3-8B (see Local Model Comparison tab) | D5: Translation / STT / TTS infrastructure — NOT a reasoning/chat LLM. Would sit in front of whatever LLM answers the question (translate Hindi/Marathi → English → answer → translate back), not replace it.
A6: Result quality | B6: Best-in-class for Indian languages — Sarvam-105B wins ~90% of pairwise comparisons on Indic benchmarks, 84% on STEM/reasoning (third-party benchmark summary, not independently re-run) | C6: Solid but a step down — 8B-class generalists (Qwen3-8B, Llama-3.1-8B) rank top-3 for Hindi/Marathi in 2026 rankings, below Sarvam’s specialized model | D6: Translation quality is strong (built for exactly this by MeitY/IITs), but does not answer questions on its own — answer quality still depends on whichever LLM sits behind it
A7: Marginal cost, 6,000-student scale | B7: ='Sarvam Cost Projection'!B31 -> 9.1034483 | C7: ='Local Model Comparison'!G9 -> 0 | D7: Unknown — no public production price; free tier covers individual/low-volume use only
A8: Available today? | B8: Yes — production-ready, has a Business rate-limit tier (1,000 req/min) explicitly for production load | C8: Yes | D8: No — blocked in review (per project status, 2026-07-30). Cannot be part of a ship-now decision.
A9: Data residency / risk | B9: Cloud dependency; student question data leaves institution infra — check against any data-residency requirement | C9: No data leaves premises, no vendor dependency, no surprise pricing changes — institution owns the ops burden and the quality ceiling | D9: Government-run — likely most durable long-term for an Indian public-sector-adjacent use case, but integration effort and price are both unknowns today
A10: License / lock-in | B10: Proprietary cloud API, pay-as-you-go, no subscription, credits never expire | C10: Apache 2.0 (Qwen3) or Meta community license (Llama 3.1) — no per-call fees regardless of volume | D10: Government DPI — terms not reviewed in this session

Sheet Sarvam Cost Projection
A1: Sarvam API Cost Projection — 6,000-Student Worst Case
A2: Worst-case = 100% adoption, ceiling usage, 0% FAQ-cache hit rate, upper-bound Hindi/Marathi share. All yellow cells are editable assumptions — see Assumptions & Sources for what is confirmed vs. estimated.
A4: Inputs (edit these)
A5: Students (minimum, worst case = 100% adoption) | B5: 6000
A6: Max questions/student (worst-case ceiling) | B6: 10
A7: % of questions in Hindi/Marathi (worst-case share) | B7: 0.45
A8: FAQ-cache hit rate assumed (worst case = 0%, every question is a fresh LLM call) | B8: 0
A9: Tokens/call — English input (question + RAG context + system prompt, estimated) | B9: 1200
A10: Tokens/call — English output (answer + citations, estimated) | B10: 300
A11: Tokens/call — Hindi/Marathi input (Devanagari tokenizes less efficiently, ~1.2x assumed) | B11: 1400
A12: Tokens/call — Hindi/Marathi output (~2.5x English, Devanagari tokenizer inflation) | B12: 750
A13: Sarvam-105B input price (₹/1M tok) — confirmed live 2026-07-30 | B13: 4
A14: Sarvam-105B cached-input price (₹/1M tok) — confirmed live 2026-07-30 (not used below; for reference) | B14: 2.5
A15: Sarvam-105B output price (₹/1M tok) — confirmed live 2026-07-30 | B15: 16
A16: Sarvam-30B input price (₹/1M tok) — THIRD-PARTY, not on Sarvam’s own current pricing page | B16: 2.5
... A18: INR → USD FX rate — NOT independently confirmed this session, placeholder | B18: 87
A20: Calculated — worst case at Max questions/student
A21: Total interactions (students × max questions/student) | B21: =B5*B6 -> 60000
A22: Effective LLM calls after cache (worst case, 0% cache hit) | B22: =B21*(1-B8) -> 60000
A23: English-language calls | B23: =B22*(1-B7) -> 33000
A24: Hindi/Marathi calls | B24: =B22*B7 -> 27000
A25: Total input tokens (English + Hindi/Marathi) | B25: =B23*B9+B24*B11 -> 77400000
A26: Total output tokens (English + Hindi/Marathi) | B26: =B23*B10+B24*B12 -> 30150000
A28: Total cost, worst case
A29: Total cost — Sarvam-105B rates (₹) | B29: =(B25/1000000)*B13+(B26/1000000)*B15 -> 792
A30: Total cost — Sarvam-30B rates (₹), if still billable | B30: =(B25/1000000)*B16+(B26/1000000)*B17 -> 495
A31: Total cost — Sarvam-105B rates ($) — THIS IS THE HEADLINE NUMBER USED ELSEWHERE | B31: =B29/B18 -> 9.1034483
A32: Total cost — Sarvam-30B rates ($), if still billable | B32: =B30/B18 -> 5.6896552
A34: Sensitivity — cost by questions/student (Sarvam-105B rates)
A35: Questions/student | B35: Total effective calls | C35: Cost (₹) | D35: Cost ($)
A36: 1 | B36: =B5*A36*(1-B8) -> 6000 | C36: =B36*(1-B7)*(B9*B13+B10*B15)/1000000+B36*B7*(B11*B13+B12*B15)/1000000 -> 79.2 | D36: =C36/B18 -> 0.91034483
A37: 3 | B37: =B5*A37*(1-B8) -> 18000 | C37: =B37*(1-B7)*(B9*B13+B10*B15)/1000000+B37*B7*(B11*B13+B12*B15)/1000000 -> 237.6 | D37: =C37/B18 -> 2.7310345
A38: 5 | B38: =B5*A38*(1-B8) -> 30000 | C38: =B38*(1-B7)*(B9*B13+B10*B15)/1000000+B38*B7*(B11*B13+B12*B15)/1000000 -> 396 | D38: =C38/B18 -> 4.5517241
A39: 10 | B39: =B5*A39*(1-B8) -> 60000 | C39: =B39*(1-B7)*(B9*B13+B10*B15)/1000000+B39*B7*(B11*B13+B12*B15)/1000000 -> 792 | D39: =C39/B18 -> 9.1034483

Sheet Local Model Comparison
A1: Self-Hosted Fallback / Local LLM Comparison
A2: Candidates to replace or complement gemma2:2b as the local fallback. VRAM at Q4_K_M quantization; GPU tier and $/mo pulled from the Hosting Options tab. Baseline = current Option A box (g4dn.xlarge).
A4: Model | B4: Params (B) | C4: VRAM need, Q4 (GB) | D4: Fits current T4 16GB box? | E4: GPU tier required | F4: $/mo (that tier) | G4: Δ vs. baseline $/mo | H4: Hindi | I4: Marathi | J4: License | K4: Notes
A5: gemma2:2b (current) | B5: 2 | C5: 2 | D5: Yes | E5: g4dn.xlarge (T4 16GB) | F5: ='Hosting Options'!I5 -> 389.98 | G5: 0 | H5: Weak, unverified for Indic | I5: Weak, unverified for Indic | J5: Gemma license | K5: Docs already call this "lower quality" — current fallback
A6: Sarvam-2B | B6: 2 | C6: 2 | D6: Yes | E6: g4dn.xlarge (T4 16GB) | F6: ='Hosting Options'!I5 -> 389.98 | G6: 0 | H6: Indic-focused | I6: Indic-focused | J6: Open-weight | K6: Same publisher as cloud primary; same size class as gemma2:2b so likely similarly limited on harder queries
A7: Airavata-7B (AI4Bharat) | B7: 7 | C7: 7 | D7: Yes | E7: g4dn.xlarge (T4 16GB) | F7: ='Hosting Options'!I5 -> 389.98 | G7: 0 | H7: Purpose-built for Hindi | I7: No Marathi support | J7: Llama 2 community license | K7: DISQUALIFYING on its own — no Marathi, and both languages are required
A8: Llama-3.1-8B-Instruct | B8: 8 | C8: 7 | D8: Yes | E8: g4dn.xlarge (T4 16GB) | F8: ='Hosting Options'!I5 -> 389.98 | G8: 0 | H8: Top-3 pick, 2026 benchmarks | I8: Top-3 pick, 2026 benchmarks | J8: Meta community license (minor commercial-use restrictions) | K8: General multilingual, not Indic-specialized
A9: Qwen3-8B (recommended to test) | B9: 8 | C9: 7 | D9: Yes | E9: g4dn.xlarge (T4 16GB) | F9: ='Hosting Options'!I5 -> 389.98 | G9: 0 | H9: Top-3 pick, 2026 benchmarks | I9: Top-3 pick, 2026 benchmarks | J9: Apache 2.0 | K9: Strong generalist, cleanest license, one-line OLLAMA_MODEL swap, $0 incremental hosting
A10: Qwen3-14B | B10: 14 | C10: 11 | D10: Tight — shared with embedding + TTS on same GPU | E10: g6.xlarge (L4 24GB) | F10: ='Hosting Options'!I6 -> 593.65 | G10: ='Hosting Options'!I6-'Hosting Options'!I5 -> 203.67 | H10: Stronger reasoning than 8B tier | I10: Stronger reasoning than 8B tier | J10: Apache 2.0 | K10: Only worth the jump if an 8B-class model fails a real eval
A11: Sarvam-105B (reference only) | B11: 105 | C11: 58 | D11: No — exceeds every single-GPU tier here | E11: Multi-GPU / A100-class — separate estimate needed | F11: N/A | G11: N/A | H11: Best-in-class, per Sarvam’s own reported benchmarks | I11: Best-in-class | J11: Apache 2.0 | K11: Same model family as the cloud primary; self-hosting it is a different cost bracket entirely, not comparable to the rows above

Sheet Hosting Options
A1: Admission Bot — Hosting Options (AWS)
A2: Live on-demand pricing, us-east-1, confirmed 2026-07-30. Compute $/mo = hourly rate × 730 hrs/month, matching the convention used in orderassist-extension-production-cost-estimate.xlsx.
A4: Option | B4: Instance | C4: vCPU / RAM | D4: GPU | E4: Storage | F4: $/hr | G4: Compute $/mo | H4: Storage $/mo | I4: Total $/mo | J4: $/year | K4: Notes
A5: Option A — GPU (recommended for production) | B5: g4dn.xlarge | C5: 4 vCPU / 16 GB | D5: NVIDIA T4, 16 GB VRAM | E5: 75 GB gp3 EBS | F5: 0.526 | G5: =F5*730 -> 383.98 | H5: 6 | I5: =G5+H5 -> 389.98 | J5: =I5*12 -> 4679.76 | K5: Runs Ollama fallback (fits an 8B model at Q4), embedding service, AI4Bharat TTS, all GPU-accelerated. Confirmed rate: economize.cloud, 2026-07-30.
A6: Option A2 — GPU upgrade (if Qwen3-14B needed) | B6: g6.xlarge | C6: 4 vCPU / 16 GB | D6: NVIDIA L4, 24 GB VRAM | E6: 75 GB gp3 EBS | F6: 0.805 | G6: =F6*730 -> 587.65 | H6: 6 | I6: =G6+H6 -> 593.65 | J6: =I6*12 -> 7123.8 | K6: Only needed if an 8B-class fallback model fails a quality eval and Qwen3-14B is required. Confirmed rate: calculator.holori.com, 2026-07-30.
A7: Option A3 — GPU alternative (reference) | B7: g5.xlarge | C7: 4 vCPU / 16 GB | D7: NVIDIA A10G, 24 GB VRAM | E7: 75 GB gp3 EBS | F7: 1.006 | G7: =F7*730 -> 734.38 | H7: 6 | I7: =G7+H7 -> 740.38 | J7: =I7*12 -> 8884.56 | K7: Pricier alternative to A2 with similar VRAM — included for comparison. Confirmed rate: economize.cloud, 2026-07-30.
A8: Option B — CPU (cheaper pilot start) | B8: c6i.2xlarge | C8: 8 vCPU / 16 GB | D8: None (CPU-only) | E8: 40 GB gp3 EBS | F8: 0.341 | G8: =F8*730 -> 248.93 | H8: 3.2 | I8: =G8+H8 -> 252.13 | J8: =I8*12 -> 3025.56 | K8: Everything on CPU; English LLM ~10-30s, Hindi/Marathi via Sarvam cloud stay fast. Repeated Qs are instant via FAQ cache. Confirmed rate: economize.cloud, 2026-07-30.
A9: Option C — Thin server + all-cloud AI | B9: t3.small | C9: 2 vCPU / 2 GB | D9: None | E9: 10 GB gp3 EBS | F9: 0.0208 | G9: =F9*730 -> 15.184 | H9: 0.8 | I9: =G9+H9 -> 15.984 | J9: =I9*12 -> 191.808 | K9: Hosts only the Python backend; routes ALL chat to Sarvam, no local fallback capability at all. Hourly rate EXTRAPOLATED from confirmed t3.large rate ($0.0832/hr) via AWS t3-family sizing steps — not independently confirmed this session.

Sheet Assumptions & Sources
A1: Assumptions, Confirmations & Sources
A2: What is confirmed live vs. estimated vs. unknown, all in one place.
A4: 1. Scale assumed | B4: 6,000 students minimum, worst case = 100% adoption (every student assumed to use the chatbot), up to 10 questions/student ceiling. Per project direction, 2026-07-30 — not derived from measured usage; there is no pilot data yet.
A6: 2. Language mix | B6: Up to 45% of questions assumed Hindi/Marathi (worst case), per project owner's stated belief — not measured. English assumed most-used overall; Tamil (also supported per MODELS_AND_DEPLOYMENT.md) is not separately modeled here.
A8: 3. Token counts | B8: Estimated, not measured. English: ~1,200 input / ~300 output tokens per call, by analogy to the extension's measured note-generation calls (~450 tok) scaled up for RAG retrieval context. Hindi/Marathi: inflated ~1.2x input / ~2.5x output vs. English, reflecting that Devanagari-script text tokenizes less efficiently than English on most BPE tokenizers (general LLM tokenization behavior, not measured for this project's specific tokenizer).
A10: 4. Sarvam pricing — CONFIRMED | B10: ₹4 input / ₹2.5 cached-input / ₹16 output per 1M tokens for the chat-completion model on Sarvam's own live pricing docs, retrieved 2026-07-30: docs.sarvam.ai/api/getting-started/pricing.md and sarvam.ai/api-pricing. This page currently lists Sarvam-105B; Sarvam-30B does NOT appear on it.
A12: 5. Sarvam-30B pricing — UNCONFIRMED / FLAG | B12: ₹2.5 input / ₹1.5 cached / ₹10 output per 1M tokens appears via a third-party aggregator (artificialanalysis.ai), not on Sarvam's own current pricing page. This project's backend/config.py hardcodes SARVAM_MODEL="sarvam-30b". Recommend emailing developer@sarvam.ai to confirm whether 30B is still billable/supported before finalizing a production budget — if it has been deprecated in favor of 105B, real cost is ~60% higher than the 30B-rate numbers would suggest (105B rates are used as the headline number in this workbook for that reason).
A14: 6. FX rate — UNCONFIRMED | B14: ₹87/$1 used throughout as a placeholder. NOT independently confirmed this session. Verify the live rate before presenting final USD figures; at this cost scale (single-digit to double-digit dollars/year) the FX rate barely moves the number, but it should still be sourced properly for a director-facing document.
A16: 7. AWS instance pricing — CONFIRMED | B16: g4dn.xlarge $0.526/hr, g5.xlarge $1.006/hr, g6.xlarge $0.805/hr, c6i.2xlarge ~$0.341/hr — all us-east-1 on-demand, retrieved live 2026-07-30 via economize.cloud / calculator.holori.com (third-party pricing aggregators, not fetched directly from aws.amazon.com/ec2/pricing due to access restrictions in this session). t3.small ($0.0208/hr) is EXTRAPOLATED from the previously-confirmed t3.large rate ($0.0832/hr, from orderassist-extension-production-cost-estimate.xlsx) via AWS t3-family sizing steps, not independently confirmed.
A18: 8. EBS storage pricing | B18: gp3 $0.08/GB/month, AWS list price — same rate used in orderassist-extension-production-cost-estimate.xlsx.
A20: 9. VRAM / quantization figures | B20: Sourced from llmrun.dev and localllm.in model-sizing guides, 2026, at Q4_K_M quantization. These do not separately budget for the embedding service and AI4Bharat TTS sharing the same GPU — real production sizing should load-test the actual box rather than rely on this estimate alone.
A22: 10. Model quality / benchmark claims | B22: Hindi/Marathi top-3 rankings and Sarvam-105B benchmark win-rates are sourced from third-party benchmark summaries (siliconflow.com, buildfastwithai.com), 2026 — these summarize Sarvam's own reported benchmarks and were not independently re-run against this project's specific prospectus/FAQ content.
A24: 11. Bhashini | B24: Free tier covers individual/low-volume developer use only. Production/commercial use requires contacting Bhashini directly — no public price exists (bhashini.ai/pricing, retrieved 2026-07-30). This project's Bhashini integration is blocked in review as of 2026-07-30; status and price are both unknown until that clears.
A26: 12. Explicitly excluded, by project direction (2026-07-30) | B26: A cost-of-human-staffed-support (ROI/labor-cost) comparison was requested, then explicitly dropped at the project owner's direction because no real institutional labor-cost baseline was available — intentionally left out of this workbook rather than estimated with an invented number. Add it back if a real figure becomes available.
A28: 13. Scope | B28: This workbook covers the admission chat/RAG pipeline only. See docs/orderassist-extension-cost-breakdown.xlsx and docs/orderassist-extension-production-cost-estimate.xlsx for the browser extension's separate, already-excluded cost estimate.
